cloudshell/__init__.py
cloudshell/networking/__init__.py
cloudshell/networking/cisco/__init__.py
cloudshell/networking/cisco/cisco_constants.py
cloudshell/networking/cisco/autoload/__init__.py
cloudshell/networking/cisco/autoload/cisco_generic_snmp_autoload.py
cloudshell/networking/cisco/autoload/cisco_snmp_if_port.py
cloudshell/networking/cisco/autoload/constants/__init__.py
cloudshell/networking/cisco/autoload/constants/snmp_constants.py
cloudshell/networking/cisco/autoload/snmp_tables/__init__.py
cloudshell/networking/cisco/autoload/snmp_tables/cisco_duplex_table.py
cloudshell/networking/cisco/autoload/snmp_tables/cisco_ports_auto_neg.py
cloudshell/networking/cisco/autoload/snmp_tables/cisco_ports_duplex.py
cloudshell/networking/cisco/autoload/snmp_tables/cisco_ports_neighbours.py
cloudshell/networking/cisco/autoload/snmp_tables/cisco_snmp_port_table.py
cloudshell/networking/cisco/autoload/table_services/__init__.py
cloudshell/networking/cisco/autoload/table_services/cisco_ports_table.py
cloudshell/networking/cisco/autoload/table_services/cisco_sys_info_table.py
cloudshell/networking/cisco/cli/__init__.py
cloudshell/networking/cisco/cli/cisco_cli_handler.py
cloudshell/networking/cisco/cli/cisco_command_modes.py
cloudshell/networking/cisco/command_actions/__init__.py
cloudshell/networking/cisco/command_actions/add_remove_vlan_actions.py
cloudshell/networking/cisco/command_actions/enable_disable_snmp_actions.py
cloudshell/networking/cisco/command_actions/iface_actions.py
cloudshell/networking/cisco/command_actions/system_actions.py
cloudshell/networking/cisco/command_templates/__init__.py
cloudshell/networking/cisco/command_templates/add_remove_vlan.py
cloudshell/networking/cisco/command_templates/configuration.py
cloudshell/networking/cisco/command_templates/enable_disable_snmp.py
cloudshell/networking/cisco/command_templates/firmware.py
cloudshell/networking/cisco/command_templates/iface.py
cloudshell/networking/cisco/errors/__init__.py
cloudshell_networking_cisco-7.0.0.dist-info/METADATA
cloudshell_networking_cisco-7.0.0.dist-info/WHEEL
cloudshell_networking_cisco-7.0.0.dist-info/top_level.txt
cloudshell_networking_cisco-7.0.0.dist-info/RECORD
