Metadata-Version: 2.1
Name: cloudshell-networking-cisco
Version: 7.0.0
Summary: QualiSystems networking cisco specific package
Home-page: http://www.qualisystems.com/
Author: QualiSystems
Author-email: info@qualisystems.com
Requires-Python: ~=3.7
Requires-Dist: cloudshell-shell-flows (<3.0,>=2.0.3)
Requires-Dist: cloudshell-shell-connectivity-flow (<4.0,>=3.1.3)
Requires-Dist: cloudshell-snmp (~=5.0)
Requires-Dist: cloudshell-snmp-autoload (<3.0,>=2.0.1)
Requires-Dist: cloudshell-cli (~=5.0)
Requires-Dist: attrs (<23,>=21)
